ctwavelet/LiftingScheme.py
ctwavelet/__init__.py
ctwavelet-1.0.5.dist-info/METADATA
ctwavelet-1.0.5.dist-info/WHEEL
ctwavelet-1.0.5.dist-info/top_level.txt
ctwavelet-1.0.5.dist-info/RECORD
