Metadata-Version: 2.1
Name: ctwavelet
Version: 1.0.5
Summary: A wavelet transform library based on Haar Lifting Scheme
Home-page: https://crypttech.com/
Author: Burak Tahtacı
Author-email: buraktahtaci@crypttech.com
License: UNKNOWN
Platform: UNKNOWN
Classifier: Programming Language :: Python :: 3
Classifier: License :: OSI Approved :: MIT License
Classifier: Operating System :: OS Independent
Requires-Python: >=3.6
